nlqweer/__init__.py
nlqweer/convtime.py
nlqweer/knmi.py
nlqweer-0.0.1.dist-info/LICENSE
nlqweer-0.0.1.dist-info/METADATA
nlqweer-0.0.1.dist-info/WHEEL
nlqweer-0.0.1.dist-info/top_level.txt
nlqweer-0.0.1.dist-info/RECORD
