Metadata-Version: 2.1
Name: nlqweer
Version: 0.0.1
Summary: weather data platform
Home-page: https://github.com/novalinq/nlqweer/
Author: minh
Author-email: minh@novalinq.com
License: UNKNOWN
Keywords: knmi,Actuele10mindataKNMIstations,nederlands
Platform: UNKNOWN
